<?xml version='1.0' encoding='UTF-8'?>
<annotation>
  <filename>1664694808.07793.jpg</filename>
  <object_num>5</object_num>
  <size>
    <width>1920</width>
    <height>1080</height>
  </size>
  <object>
    <name>vessel</name>
    <difficult>0</difficult>
    <bndbox>
      <xmin>966</xmin>
      <ymin>524</ymin>
      <xmax>1031</xmax>
      <ymax>567</ymax>
    </bndbox>
  </object>
  <object>
    <name>vessel</name>
    <difficult>0</difficult>
    <bndbox>
      <xmin>868</xmin>
      <ymin>825</ymin>
      <xmax>1320</xmax>
      <ymax>1079</ymax>
    </bndbox>
  </object>
  <object>
    <name>vessel</name>
    <difficult>0</difficult>
    <bndbox>
      <xmin>976</xmin>
      <ymin>505</ymin>
      <xmax>1014</xmax>
      <ymax>524</ymax>
    </bndbox>
  </object>
  <object>
    <name>pier</name>
    <difficult>0</difficult>
    <bndbox>
      <xmin>1045</xmin>
      <ymin>487</ymin>
      <xmax>1051</xmax>
      <ymax>495</ymax>
    </bndbox>
  </object>
  <object>
    <name>pier</name>
    <difficult>0</difficult>
    <bndbox>
      <xmin>991</xmin>
      <ymin>487</ymin>
      <xmax>996</xmax>
      <ymax>498</ymax>
    </bndbox>
  </object>
</annotation>
