<?xml version='1.0' encoding='UTF-8'?>
<annotation>
  <filename>1664694541.92690.jpg</filename>
  <object_num>2</object_num>
  <size>
    <width>1920</width>
    <height>1080</height>
  </size>
  <object>
    <name>vessel</name>
    <difficult>0</difficult>
    <bndbox>
      <xmin>732</xmin>
      <ymin>526</ymin>
      <xmax>846</xmax>
      <ymax>561</ymax>
    </bndbox>
  </object>
  <object>
    <name>pier</name>
    <difficult>0</difficult>
    <bndbox>
      <xmin>849</xmin>
      <ymin>524</ymin>
      <xmax>877</xmax>
      <ymax>532</ymax>
    </bndbox>
  </object>
</annotation>
