<?xml version='1.0' encoding='UTF-8'?>
<annotation>
  <filename>1663830345.95953.jpg</filename>
  <object_num>2</object_num>
  <size>
    <width>1920</width>
    <height>1080</height>
  </size>
  <object>
    <name>ship</name>
    <difficult>0</difficult>
    <bndbox>
      <xmin>681</xmin>
      <ymin>427</ymin>
      <xmax>932</xmax>
      <ymax>499</ymax>
    </bndbox>
  </object>
  <object>
    <name>ship</name>
    <difficult>0</difficult>
    <bndbox>
      <xmin>1060</xmin>
      <ymin>432</ymin>
      <xmax>1118</xmax>
      <ymax>458</ymax>
    </bndbox>
  </object>
</annotation>
