<?xml version='1.0' encoding='UTF-8'?>
<annotation>
  <filename>1664438172.41660.jpg</filename>
  <object_num>2</object_num>
  <size>
    <width>1920</width>
    <height>1080</height>
  </size>
  <object>
    <name>boat</name>
    <difficult>0</difficult>
    <bndbox>
      <xmin>989</xmin>
      <ymin>390</ymin>
      <xmax>1061</xmax>
      <ymax>411</ymax>
    </bndbox>
  </object>
  <object>
    <name>ship</name>
    <difficult>0</difficult>
    <bndbox>
      <xmin>1476</xmin>
      <ymin>342</ymin>
      <xmax>1711</xmax>
      <ymax>381</ymax>
    </bndbox>
  </object>
</annotation>
